Metadata-Version: 2.1
Name: hookshothq
Version: 0.0.1
Summary: Python bindings for the Hookshot API
Home-page: https://www.hookshothq.com
Author: Hookshot
Author-email: support@hookshothq.com
License: UNKNOWN
Platform: UNKNOWN
Classifier: Programming Language :: Python :: 3
Classifier: License :: OSI Approved :: MIT License
Classifier: Operating System :: OS Independent
Requires-Python: >=3.6
